linear_regression_bendou/__init__.py
linear_regression_bendou/linreg.py
linear_regression_bendou/setup.py
linear_regression_bendou-1.0.0.dist-info/METADATA
linear_regression_bendou-1.0.0.dist-info/WHEEL
linear_regression_bendou-1.0.0.dist-info/top_level.txt
linear_regression_bendou-1.0.0.dist-info/RECORD
