Metadata-Version: 2.1
Name: linear_regression_bendou
Version: 1.0.0
Summary: An awesome package that implements single linear regression
Home-page: http://pypi.python.org/pypi/linear_regression_bendou/
Author: Ma Ben
Author-email: ambesi2026@gmail.com
License: linear_regression_bendou/LICENSE.txt
Requires-Dist: linear-regression-bendou
